<?xml version="1.0" encoding="utf-8"?>
<!DOCTYPE hibernate-mapping PUBLIC "-//Hibernate/Hibernate Mapping DTD 3.0//EN"
"http://hibernate.sourceforge.net/hibernate-mapping-3.0.dtd">
<!-- 
    Mapping file autogenerated by MyEclipse Persistence Tools
-->
<hibernate-mapping>
    <class name="basicdata.database.TBasicdataProduct" table="t_basicdata_product" dynamic-insert="true" dynamic-update="true" >
        <id name="id" type="java.lang.Integer">
            <column name="id" />
            <generator class="identity" />
        </id>
        <property name="name" type="java.lang.String">
            <column name="name" length="20" />
        </property>
        <property name="state" type="java.lang.String">
            <column name="state" length="20" />
        </property>
        <property name="createUser" type="java.lang.Integer">
            <column name="create_user" />
        </property>
        <property name="createDate" type="java.lang.String">
            <column name="create_date" length="20" />
        </property>
        <property name="updateUser" type="java.lang.Integer">
            <column name="update_user" />
        </property>
        <property name="updateDate" type="java.lang.String">
            <column name="update_date" length="20" />
        </property>
        <property name="exe1" type="java.lang.Integer">
            <column name="exe1" length="20" default="0"/>
        </property>
        <property name="exe2" type="java.lang.Integer">
            <column name="exe2" length="20" default="0"/>
        </property>
        <property name="exe3" type="java.lang.Integer">
            <column name="exe3" length="20" default="0"/>
        </property>
        <property name="exe4" type="java.lang.Integer">
            <column name="exe4" length="20" default="0"/>
        </property>
        <property name="exe5" type="java.lang.Integer">
            <column name="exe5" length="20" default="0"/>
        </property>
        <property name="exe6" type="java.lang.Integer">
            <column name="exe6" length="20" default="0"/>
        </property>
        <property name="exe7" type="java.lang.Integer">
            <column name="exe7" length="20" default="0"/>
        </property>
        <property name="exe8" type="java.lang.Integer">
            <column name="exe8" length="20" default="0"/>
        </property>
    </class>
</hibernate-mapping>
